Cargo.toml
LICENSE
README.md
async_server_ops-1.0.4.dist-info/METADATA
async_server_ops-1.0.4.dist-info/WHEEL
async_server_ops-1.0.4.dist-info/licenses/LICENSE
async_server_ops/__init__.py
async_server_ops/async_server_ops.pyd
pyproject.toml
async_server_ops-1.0.4.dist-info/RECORD
