Metadata-Version: 2.4
Name: async-server-ops
Version: 1.0.4
Classifier: Programming Language :: Python :: 3
Classifier: Programming Language :: Python :: 3 :: Only
Classifier: Programming Language :: Python :: 3.8
Classifier: Programming Language :: Python :: 3.9
Classifier: Programming Language :: Python :: 3.10
Classifier: Programming Language :: Python :: 3.11
Classifier: Programming Language :: Python :: 3.12
Classifier: Programming Language :: Rust
Classifier: License :: OSI Approved :: MIT License
License-File: LICENSE
Summary: Async remote file ops over SSH (scp) with robust defaults and Python bindings
License: MIT
Requires-Python: >=3.8
